orrin/__init__.py
orrin/cli.py
orrin_cli-0.1.7.dist-info/licenses/LICENSE
orrin_cli-0.1.7.dist-info/METADATA
orrin_cli-0.1.7.dist-info/WHEEL
orrin_cli-0.1.7.dist-info/entry_points.txt
orrin_cli-0.1.7.dist-info/top_level.txt
orrin_cli-0.1.7.dist-info/RECORD
