Metadata-Version: 2.4
Name: orrin-cli
Version: 0.1.7
Summary: Orrin CLI
Requires-Python: >=3.9
License-File: LICENSE
Requires-Dist: typer
Requires-Dist: requests
Requires-Dist: platformdirs
Dynamic: license-file
